mcp_gsuite/__init__.py
mcp_gsuite/auto_update.py
mcp_gsuite/calendar.py
mcp_gsuite/gauth.py
mcp_gsuite/gmail.py
mcp_gsuite/server.py
mcp_gsuite/toolhandler.py
mcp_gsuite/tools_calendar.py
mcp_gsuite/tools_gmail.py
mcp_google_workspace-0.7.1.dist-info/METADATA
mcp_google_workspace-0.7.1.dist-info/WHEEL
mcp_google_workspace-0.7.1.dist-info/entry_points.txt
mcp_google_workspace-0.7.1.dist-info/licenses/LICENSE
mcp_google_workspace-0.7.1.dist-info/RECORD
