Metadata-Version: 2.4
Name: mcp-google-workspace
Version: 0.7.1
Summary: MCP Server to connect to Google Workspace (Gmail & Calendar)
Author-email: Olivier de Beuf de Rijcker <olivier@markov.bot>
License-File: LICENSE
Requires-Python: >=3.13
Requires-Dist: aiohttp>=3.9.0
Requires-Dist: beautifulsoup4>=4.12.3
Requires-Dist: google-api-python-client>=2.154.0
Requires-Dist: httplib2>=0.22.0
Requires-Dist: mcp>=1.3.0
Requires-Dist: oauth2client==4.1.3
Requires-Dist: packaging>=23.0
Requires-Dist: python-dotenv>=1.0.1
Requires-Dist: pytz>=2024.2
Requires-Dist: requests>=2.32.3
Requires-Dist: twine>=6.1.0
